gbnn/GBNN.py
gbnn/__init__.py
gbnn/cross_validation.py
GBNN-0.0.2.dist-info/LICENSE
GBNN-0.0.2.dist-info/METADATA
GBNN-0.0.2.dist-info/WHEEL
GBNN-0.0.2.dist-info/top_level.txt
GBNN-0.0.2.dist-info/RECORD
