Metadata-Version: 2.1
Name: GBNN
Version: 0.0.2
Summary: Gradient Boosted Neural Network.
Home-page: UNKNOWN
Author: Seyedsaman Emami, Gonzalo Martínez-Muñoz
Author-email: emami.seyedsaman@uam.es, gonzalo.martinez@uam.es
License: UNKNOWN
Platform: UNKNOWN
Classifier: Development Status :: 1 - Planning
Classifier: Intended Audience :: Developers
Classifier: Programming Language :: Python :: 3
Classifier: Operating System :: Unix
Classifier: Operating System :: MacOS :: MacOS X
Classifier: Operating System :: Microsoft :: Windows
License-File: LICENSE
Requires-Dist: numpy
Requires-Dist: scipy
Requires-Dist: sklearn
